MANIFEST.in
distribute_setup.py
setup.py
ordrinfork/__init__.py
ordrinfork/api.py
ordrinfork/api_helper.py
ordrinfork/mutate.py
ordrinfork/schemas.json
ordrinfork.egg-info/PKG-INFO
ordrinfork.egg-info/SOURCES.txt
ordrinfork.egg-info/dependency_links.txt
ordrinfork.egg-info/requires.txt
ordrinfork.egg-info/top_level.txt